colorifier/__init__.py
colorifier/model.pkl
colorifier/predict.py
colorifier/train.py
colorifier/util.py
colorifier-1.3.dist-info/METADATA
colorifier-1.3.dist-info/RECORD
colorifier-1.3.dist-info/WHEEL
colorifier-1.3.dist-info/top_level.txt
