Metadata-Version: 2.1
Name: colorifier
Version: 1.3
Summary: Classifier for colors
Home-page: https://github.com/ofrik/colorifier
Author: Ofri Masad
Author-email: ofrik89@gmail.com
License: UNKNOWN
Platform: UNKNOWN
Classifier: Programming Language :: Python :: 3
Classifier: License :: OSI Approved :: MIT License
Classifier: Operating System :: OS Independent
